README.rst
setup.cfg
setup.py
bocco/__init__.py
bocco/api.py
bocco/cli.py
bocco/models.py
bocco/web.py
bocco.egg-info/PKG-INFO
bocco.egg-info/SOURCES.txt
bocco.egg-info/dependency_links.txt
bocco.egg-info/requires.txt
bocco.egg-info/top_level.txt