Metadata-Version: 1.0
Name: bocco
Version: 0.1.4
Summary: BOCCO API Client
Home-page: https://github.com/YUKAI/bocco-api-python
Author: wkiryu
Author-email: kiryu@ux-xu.com
License: UNKNOWN
Keywords: bocco
Platform: UNKNOWN
